<RespuestaAutorizacionComprobante>
	<claveAccesoConsultada>1911202001099280734200120010060000008501030559915</claveAccesoConsultada>
	<numeroComprobantes>1</numeroComprobantes>
	<autorizaciones>
		<autorizacion>
			<estado>AUTORIZADO</estado>
			<numeroAutorizacion>1911202001099280734200120010060000008501030559915</numeroAutorizacion>
			<fechaAutorizacion>2020-11-19T15:29:08-05:00</fechaAutorizacion>
			<ambiente>PRODUCCION</ambiente>
			<comprobante><![CDATA[<RespuestaAutorizacionComprobante>
	<claveAccesoConsultada>1911202001099280734200120010060000008501030559915</claveAccesoConsultada>
	<numeroComprobantes>1</numeroComprobantes>
	<autorizaciones>
		<autorizacion>
			<estado>AUTORIZADO</estado>
			<numeroAutorizacion>1911202001099280734200120010060000008501030559915</numeroAutorizacion>
			<fechaAutorizacion>2020-11-19T15:29:08-05:00</fechaAutorizacion>
			<ambiente>PRODUCCION</ambiente>
			<comprobante><![CDATA[<RespuestaAutorizacionComprobante>
	<claveAccesoConsultada>1911202001099280734200120010060000008501030559915</claveAccesoConsultada>
	<numeroComprobantes>1</numeroComprobantes>
	<autorizaciones>
		<autorizacion>
			<estado>AUTORIZADO</estado>
			<numeroAutorizacion>1911202001099280734200120010060000008501030559915</numeroAutorizacion>
			<fechaAutorizacion>2020-11-19T15:29:08-05:00</fechaAutorizacion>
			<ambiente>PRODUCCION</ambiente>
			<comprobante><![CDATA[<?xml version="1.0" encoding="ISO-8859-1"?>
<factura id="comprobante" version="1.0.0">
  <infoTributaria>
    <ambiente>2</ambiente>
    <tipoEmision>1</tipoEmision>
    <razonSocial>INSTITUTO DE MICROCIRUGIA OCULAR INMICROCSA SA</razonSocial>
    <nombreComercial>INMICROCSA SA</nombreComercial>
    <ruc>0992807342001</ruc>
    <claveAcceso>1911202001099280734200120010060000008501030559915</claveAcceso>
    <codDoc>01</codDoc>
    <estab>001</estab>
    <ptoEmi>006</ptoEmi>
    <secuencial>000000850</secuencial>
    <dirMatriz>Km 12.5 Av. Leon Febres Cordero junto a Piazza Villa Club Edificio: Clinica de la Piazza.</dirMatriz>
  </infoTributaria>
  <infoFactura>
    <fechaEmision>19/11/2020</fechaEmision>
    <dirEstablecimiento>Km 12.5 Av. Leon Febres Cordero junto a Piazza Villa Club Edificio: Clinica de la Piazza.</dirEstablecimiento>
    <obligadoContabilidad>SI</obligadoContabilidad>
    <tipoIdentificacionComprador>04</tipoIdentificacionComprador>
    <razonSocialComprador>KATTYA OLIVARES</razonSocialComprador>
    <identificacionComprador>0914360318001</identificacionComprador>
    <direccionComprador>SANTA MARIA DE CASA GRNADE MZ C V1</direccionComprador>
    <totalSinImpuestos>80.00</totalSinImpuestos>
    <totalDescuento>40.00</totalDescuento>
    <totalConImpuestos>
      <totalImpuesto>
        <codigo>2</codigo>
        <codigoPorcentaje>0</codigoPorcentaje>
        <descuentoAdicional>0.00</descuentoAdicional>
        <baseImponible>80.00</baseImponible>
        <valor>0.00</valor>
      </totalImpuesto>
    </totalConImpuestos>
    <propina>0</propina>
    <importeTotal>80.00</importeTotal>
    <moneda>DOLAR</moneda>
  </infoFactura>
  <detalles>
    <detalle>
      <codigoPrincipal>76514</codigoPrincipal>
      <descripcion>Paquimetria corneal, uni o bilateral (determinacion de grosor corneal).</descripcion>
      <cantidad>1</cantidad>
      <precioUnitario>60.00</precioUnitario>
      <descuento>20.00</descuento>
      <precioTotalSinImpuesto>40.00</precioTotalSinImpuesto>
      <impuestos>
        <impuesto>
          <codigo>2</codigo>
          <codigoPorcentaje>0</codigoPorcentaje>
          <tarifa>0.00</tarifa>
          <baseImponible>40.00</baseImponible>
          <valor>0.00</valor>
        </impuesto>
      </impuestos>
    </detalle>
    <detalle>
      <codigoPrincipal>76514</codigoPrincipal>
      <descripcion>Paquimetria corneal, uni o bilateral (determinacion de grosor corneal).</descripcion>
      <cantidad>1</cantidad>
      <precioUnitario>60.00</precioUnitario>
      <descuento>20.00</descuento>
      <precioTotalSinImpuesto>40.00</precioTotalSinImpuesto>
      <impuestos>
        <impuesto>
          <codigo>2</codigo>
          <codigoPorcentaje>0</codigoPorcentaje>
          <tarifa>0.00</tarifa>
          <baseImponible>40.00</baseImponible>
          <valor>0.00</valor>
        </impuesto>
      </impuestos>
    </detalle>
  </detalles>
  <infoAdicional>
    <campoAdicional nombre="Direccion">SANTA MARIA DE CASA GRNADE MZ C V1</campoAdicional>
    <campoAdicional nombre="Telefono">0993680379</campoAdicional>
    <campoAdicional nombre="Email">katty-olivares@hotmail.com</campoAdicional>
    <campoAdicional nombre="Plan">CLIENTES PARTICULARES </campoAdicional>
    <campoAdicional nombre="CampoAdicional">AGENTE DE RETENCION SEGUN RESOLUCION No. NAC-DGERCGC20-0000001</campoAdicional>
  </infoAdicional>
</factura>
]]>
			</comprobante>
		</autorizacion>
	</autorizaciones>
</RespuestaAutorizacionComprobante>]]>
			</comprobante>
		</autorizacion>
	</autorizaciones>
</RespuestaAutorizacionComprobante>]]>
			</comprobante>
		</autorizacion>
	</autorizaciones>
</RespuestaAutorizacionComprobante>